{"results": [{"data": {"petition": {"id": "21409522", "slug": "warner-brothers-leave-ezra-miller-as-the-flash-and-in-fantastic-beasts-3", "user": {"id": "1072982128", "displayName": "\u0410\u043d\u0434\u0440\u0435\u0439 \u0410\u043d\u0434\u0440\u0435\u0435\u0432", "photo": {"id": "223518479", "userSmall": {"url": "//assets.change.org/photos/7/ps/ts/eBPSTShOUAGhCJk-48x48-noPad.jpg?1586335248", "processing": false}}}, "organization": null, "updatesConnection": {"nodes": [{"__typename": "MilestonePetitionUpdate", "id": "30404169", "createdAt": "2022-04-03T15:12:41.000Z", "signatureCount": 500}, {"__typename": "MilestonePetitionUpdate", "id": "26421227", "createdAt": "2020-04-21T11:30:15.000Z", "signatureCount": 250}, {"__typename": "MilestonePetitionUpdate", "id": "26402471", "createdAt": "2020-04-19T13:05:43.000Z", "signatureCount": 200}, {"__typename": "MilestonePetitionUpdate", "id": "26331779", "createdAt": "2020-04-12T17:36:03.000Z", "signatureCount": 100}, {"__typename": "MilestonePetitionUpdate", "id": "26314385", "createdAt": "2020-04-10T14:40:34.000Z", "signatureCount": 50}, {"__typename": "MilestonePetitionUpdate", "id": "26293019", "createdAt": "2020-04-08T12:39:07.000Z", "signatureCount": 25}, {"__typename": "MilestonePetitionUpdate", "id": "26292887", "createdAt": "2020-04-08T12:19:27.000Z", "signatureCount": 10}, {"__typename": "MilestonePetitionUpdate", "id": "26292668", "createdAt": "2020-04-08T11:46:12.000Z", "signatureCount": 5}], "pageInfo": {"endCursor": "YXJyYXljb25uZWN0aW9uOjc=", "hasNextPage": false}}}}}], "count": 1, "cursors": [""]}