{"results": [{"data": {"petition": {"id": "25787326", "slug": "warner-brothers-remove-amber-heard-as-mere-in-aqua-man-2", "user": {"id": "1163706232", "displayName": "Dylan Saxon", "photo": {"id": "224847044", "userSmall": {"url": "//assets.change.org/photos/1/wo/ge/QdWogeoOImOGSiF-48x48-noPad.jpg?1605102637", "processing": false}}}, "organization": null, "updatesConnection": {"nodes": [{"__typename": "MilestonePetitionUpdate", "id": "30817916", "createdAt": "2022-08-09T15:38:19.000Z", "signatureCount": 750}, {"__typename": "MilestonePetitionUpdate", "id": "30515229", "createdAt": "2022-05-05T04:02:46.000Z", "signatureCount": 500}, {"__typename": "MilestonePetitionUpdate", "id": "28637780", "createdAt": "2021-03-02T12:14:05.000Z", "signatureCount": 250}, {"__typename": "MilestonePetitionUpdate", "id": "28287794", "createdAt": "2020-12-31T13:21:39.000Z", "signatureCount": 200}, {"__typename": "MilestonePetitionUpdate", "id": "28153966", "createdAt": "2020-12-02T05:31:46.000Z", "signatureCount": 100}, {"__typename": "MilestonePetitionUpdate", "id": "28100796", "createdAt": "2020-11-21T05:50:48.000Z", "signatureCount": 50}, {"__typename": "MilestonePetitionUpdate", "id": "28072662", "createdAt": "2020-11-16T00:53:55.000Z", "signatureCount": 25}, {"__typename": "MilestonePetitionUpdate", "id": "28056174", "createdAt": "2020-11-12T13:06:37.000Z", "signatureCount": 10}, {"__typename": "MilestonePetitionUpdate", "id": "28050445", "createdAt": "2020-11-11T14:45:08.000Z", "signatureCount": 5}], "pageInfo": {"endCursor": "YXJyYXljb25uZWN0aW9uOjg=", "hasNextPage": false}}}}}], "count": 1, "cursors": [""]}