{"results": [{"data": {"petition": {"id": "33172054", "slug": "disney-should-apologize-to-johnny-depp", "user": {"id": "1161908464", "displayName": "Makenzie Leaswitch", "photo": null}, "organization": null, "updatesConnection": {"nodes": [{"__typename": "MilestonePetitionUpdate", "id": "30616475", "createdAt": "2022-06-01T22:54:05.000Z", "signatureCount": 2000}, {"__typename": "MilestonePetitionUpdate", "id": "30589886", "createdAt": "2022-05-25T13:00:26.000Z", "signatureCount": 1500}, {"__typename": "MilestonePetitionUpdate", "id": "30571447", "createdAt": "2022-05-19T23:11:09.000Z", "signatureCount": 1000}, {"__typename": "MilestonePetitionUpdate", "id": "30562612", "createdAt": "2022-05-17T22:23:17.000Z", "signatureCount": 750}, {"__typename": "MilestonePetitionUpdate", "id": "30555448", "createdAt": "2022-05-16T02:05:59.000Z", "signatureCount": 500}, {"__typename": "MilestonePetitionUpdate", "id": "30551996", "createdAt": "2022-05-14T21:00:41.000Z", "signatureCount": 250}, {"__typename": "MilestonePetitionUpdate", "id": "30551272", "createdAt": "2022-05-14T16:05:43.000Z", "signatureCount": 200}, {"__typename": "MilestonePetitionUpdate", "id": "30547902", "createdAt": "2022-05-13T16:27:08.000Z", "signatureCount": 100}, {"__typename": "MilestonePetitionUpdate", "id": "30523348", "createdAt": "2022-05-07T04:19:43.000Z", "signatureCount": 50}, {"__typename": "MilestonePetitionUpdate", "id": "30503833", "createdAt": "2022-05-02T11:53:25.000Z", "signatureCount": 25}, {"__typename": "MilestonePetitionUpdate", "id": "30492890", "createdAt": "2022-04-28T23:57:45.000Z", "signatureCount": 10}, {"__typename": "MilestonePetitionUpdate", "id": "30491298", "createdAt": "2022-04-28T16:45:46.000Z", "signatureCount": 5}], "pageInfo": {"endCursor": "YXJyYXljb25uZWN0aW9uOjEx", "hasNextPage": false}}}}}], "count": 1, "cursors": [""]}