{"results": [{"data": {"petition": {"id": "33248029", "slug": "replace-amber-heard-from-aquaman-2-with-makenzie-lauren-\ufe0f-take-a-stand-against-d-omestic-violance", "user": {"id": "11627721", "displayName": "Sue White", "photo": {"id": "13538983", "userSmall": {"url": "//assets.change.org/photos/8/pu/dl/pBPUdlJWiYktvNC-48x48-noPad.jpg?1520654807", "processing": false}}}, "organization": null, "updatesConnection": {"nodes": [{"__typename": "MilestonePetitionUpdate", "id": "30692539", "createdAt": "2022-06-25T07:56:49.000Z", "signatureCount": 4000}, {"__typename": "StarterPetitionUpdate", "id": "30621859", "createdAt": "2022-06-03T11:27:20.000Z", "title": "THANK YOU!! Domestic violence has NO GENDER!", "description": "<p>Thank You ALL for your Support! We passed 4,000 signatures! Share, Share, Share with Family, Friends and on Social Media! The Support has come World Wide, together we CAN make a Difference! We appreciate All who have signed and those yet to sign!!! Thank you!!!</p>\n<p>Domestic violence has NO GENDER!</p>\n<p>\u00a0</p>", "photo": null, "video": null, "embeddedMedia": null}, {"__typename": "MilestonePetitionUpdate", "id": "30620127", "createdAt": "2022-06-02T21:43:57.000Z", "signatureCount": 4000}, {"__typename": "MilestonePetitionUpdate", "id": "30620124", "createdAt": "2022-06-02T21:42:53.000Z", "signatureCount": 4000}, {"__typename": "MilestonePetitionUpdate", "id": "30620122", "createdAt": "2022-06-02T21:41:55.000Z", "signatureCount": 4000}, {"__typename": "MilestonePetitionUpdate", "id": "30620115", "createdAt": "2022-06-02T21:41:03.000Z", "signatureCount": 4000}, {"__typename": "StarterPetitionUpdate", "id": "30609827", "createdAt": "2022-05-31T06:19:57.000Z", "title": "A Big Shout Out to say THANK YOU  for Your Support!", "description": "<p>We just passed the 3,000th signature!!!</p>\n<p>Thank you SO MUCH for Your Continued Support! Please continue to Share this petition with your Family, Friends &amp; Social Media!\u00a0</p>\n<p>Domestic Violence has NO GENDER!</p>\n<p>Amber Heard Needs to Be Replaced!</p>\n<p>Thank you!</p>", "photo": null, "video": null, "embeddedMedia": null}, {"__typename": "MilestonePetitionUpdate", "id": "30609592", "createdAt": "2022-05-31T04:07:38.000Z", "signatureCount": 3000}, {"__typename": "MilestonePetitionUpdate", "id": "30595214", "createdAt": "2022-05-26T16:10:04.000Z", "signatureCount": 2500}, {"__typename": "StarterPetitionUpdate", "id": "30583849", "createdAt": "2022-05-23T21:47:12.000Z", "title": "Thank you! Please keep Sharing!!", "description": "<p>Thank you to all who have Signed and Shared! We just passes the 2,000th signature!! Let's keep going! Please contine to Share with Family and Friends and on Social Meida!! Thank you for your continued support!\u00a0</p>", "photo": null, "video": null, "embeddedMedia": null}, {"__typename": "MilestonePetitionUpdate", "id": "30580296", "createdAt": "2022-05-22T20:59:56.000Z", "signatureCount": 2000}, {"__typename": "StarterPetitionUpdate", "id": "30571697", "createdAt": "2022-05-20T00:36:26.000Z", "title": "\u2764\ufe0f Thank you for your continued support \u2764\ufe0f", "description": "<p>We passed the 1,500 mark! We have lots more to go! With you continued Support by Sharing on Social Media and with Family &amp; Friends, We WILL Have Our Voices Heard! 10 minutes of screen time is to much time for Amber Heard! Justice for Johnny Depp, he had it taken all!</p>\n<p>#justiceforjohhnydepp</p>\n<p>Please keep Sharing Everywhere!!</p>\n<p>\u2764\ufe0f Thank you\u00a0</p>", "photo": null, "video": null, "embeddedMedia": null}], "pageInfo": {"endCursor": "YXJyYXljb25uZWN0aW9uOjEx", "hasNextPage": true}}}}}, {"data": {"petition": {"id": "33248029", "slug": "replace-amber-heard-from-aquaman-2-with-makenzie-lauren-\ufe0f-take-a-stand-against-d-omestic-violance", "user": {"id": "11627721", "displayName": "Sue White", "photo": {"id": "13538983", "userSmall": {"url": "//assets.change.org/photos/8/pu/dl/pBPUdlJWiYktvNC-48x48-noPad.jpg?1520654807", "processing": false}}}, "organization": null, "updatesConnection": {"nodes": [{"__typename": "MilestonePetitionUpdate", "id": "30567562", "createdAt": "2022-05-19T01:42:35.000Z", "signatureCount": 1500}, {"__typename": "MilestonePetitionUpdate", "id": "30567095", "createdAt": "2022-05-18T22:57:21.000Z", "signatureCount": 1500}, {"__typename": "StarterPetitionUpdate", "id": "30558585", "createdAt": "2022-05-16T22:43:17.000Z", "title": "\u2764\ufe0f Thank you for your continued support! \u2764\ufe0f", "description": "<p>\u2764\ufe0f\u00a0 Over 1,000 signatures! You all have been Amazing showing your support! Thank you so much! Please continue to share this petition on Social Media and with your family &amp; friends! Thank you and God Bless! \u2764\ufe0f\u00a0</p>", "photo": null, "video": null, "embeddedMedia": null}, {"__typename": "MilestonePetitionUpdate", "id": "30552903", "createdAt": "2022-05-15T06:49:16.000Z", "signatureCount": 1000}, {"__typename": "MilestonePetitionUpdate", "id": "30552895", "createdAt": "2022-05-15T06:43:58.000Z", "signatureCount": 1000}, {"__typename": "MilestonePetitionUpdate", "id": "30551569", "createdAt": "2022-05-14T17:57:52.000Z", "signatureCount": 750}, {"__typename": "MilestonePetitionUpdate", "id": "30549616", "createdAt": "2022-05-14T01:49:01.000Z", "signatureCount": 500}, {"__typename": "MilestonePetitionUpdate", "id": "30549015", "createdAt": "2022-05-13T21:30:33.000Z", "signatureCount": 500}, {"__typename": "MilestonePetitionUpdate", "id": "30546522", "createdAt": "2022-05-13T08:22:15.000Z", "signatureCount": 250}, {"__typename": "MilestonePetitionUpdate", "id": "30545636", "createdAt": "2022-05-13T00:45:41.000Z", "signatureCount": 200}, {"__typename": "StarterPetitionUpdate", "id": "30544602", "createdAt": "2022-05-12T19:16:39.000Z", "title": "\u2764\ufe0f Thank you all for your support \u2764\ufe0f", "description": "<p>Thank you all for showing your support,\u00a0 we just past the 150 mark! Please Share this petition with your Family &amp; Friends! \u2764\ufe0f\u00a0</p>\n<p>We greatly appreciate your time and support!</p>", "photo": null, "video": null, "embeddedMedia": null}, {"__typename": "MilestonePetitionUpdate", "id": "30539822", "createdAt": "2022-05-11T17:23:18.000Z", "signatureCount": 100}], "pageInfo": {"endCursor": "YXJyYXljb25uZWN0aW9uOjIz", "hasNextPage": true}}}}}, {"data": {"petition": {"id": "33248029", "slug": "replace-amber-heard-from-aquaman-2-with-makenzie-lauren-\ufe0f-take-a-stand-against-d-omestic-violance", "user": {"id": "11627721", "displayName": "Sue White", "photo": {"id": "13538983", "userSmall": {"url": "//assets.change.org/photos/8/pu/dl/pBPUdlJWiYktvNC-48x48-noPad.jpg?1520654807", "processing": false}}}, "organization": null, "updatesConnection": {"nodes": [{"__typename": "MilestonePetitionUpdate", "id": "30534928", "createdAt": "2022-05-10T14:47:39.000Z", "signatureCount": 50}, {"__typename": "MilestonePetitionUpdate", "id": "30526036", "createdAt": "2022-05-07T23:29:07.000Z", "signatureCount": 25}, {"__typename": "MilestonePetitionUpdate", "id": "30521255", "createdAt": "2022-05-06T16:11:13.000Z", "signatureCount": 10}, {"__typename": "MilestonePetitionUpdate", "id": "30518815", "createdAt": "2022-05-06T01:08:26.000Z", "signatureCount": 5}], "pageInfo": {"endCursor": "YXJyYXljb25uZWN0aW9uOjI3", "hasNextPage": false}}}}}], "count": 3, "cursors": ["", "YXJyYXljb25uZWN0aW9uOjEx", "YXJyYXljb25uZWN0aW9uOjIz"]}