{"results": [{"data": {"petition": {"id": "33174933", "slug": "remove-amber-heard-as-an-aclu-ambassador", "user": {"id": "6021991", "displayName": "Georgia Ota", "photo": {"id": "215978692", "userSmall": {"url": "//assets.change.org/photos/4/rn/dh/MMRnDHHbRdZoCWu-48x48-noPad.jpg?1516582206", "processing": false}}}, "organization": null, "updatesConnection": {"nodes": [{"__typename": "MilestonePetitionUpdate", "id": "30675363", "createdAt": "2022-06-20T03:03:53.000Z", "signatureCount": 17500}, {"__typename": "MilestonePetitionUpdate", "id": "30623847", "createdAt": "2022-06-03T22:14:57.000Z", "signatureCount": 15000}, {"__typename": "MilestonePetitionUpdate", "id": "30615563", "createdAt": "2022-06-01T18:14:23.000Z", "signatureCount": 12500}, {"__typename": "MilestonePetitionUpdate", "id": "30611895", "createdAt": "2022-05-31T18:09:27.000Z", "signatureCount": 10000}, {"__typename": "MilestonePetitionUpdate", "id": "30609723", "createdAt": "2022-05-31T05:27:50.000Z", "signatureCount": 9000}, {"__typename": "MilestonePetitionUpdate", "id": "30601917", "createdAt": "2022-05-28T11:37:05.000Z", "signatureCount": 8000}, {"__typename": "MilestonePetitionUpdate", "id": "30595607", "createdAt": "2022-05-26T17:34:49.000Z", "signatureCount": 7500}, {"__typename": "MilestonePetitionUpdate", "id": "30580254", "createdAt": "2022-05-22T20:41:21.000Z", "signatureCount": 7000}, {"__typename": "MilestonePetitionUpdate", "id": "30559589", "createdAt": "2022-05-17T05:46:23.000Z", "signatureCount": 6000}, {"__typename": "StarterPetitionUpdate", "id": "30551678", "createdAt": "2022-05-14T18:35:49.000Z", "title": "Over 5000 signatures!!", "description": "<p>Congratulations! We have over 5000 signatures! In my last update I said that I would email the ACLU when we hit 1000 but we had such momentum I decided to wait a little longer, glad I did. Having hit the 5000 mark today I've drafted the email and downloaded all signatures and comments (as of this morning) and will be sending the email today.\u00a0 My communication to the ACLU will include a link to our petition, so feel free to continue to share the message, hopefully they'll check it out and see that people feel strongly about removing Ms. Heard from the list of ambassadors.\u00a0 I will post another update tomorrow with the content of that email.\u00a0 PS - signatures came from 77 countries!! The world is looking to the ACLU to do the right thing.</p>", "photo": null, "video": null, "embeddedMedia": null}, {"__typename": "MilestonePetitionUpdate", "id": "30549904", "createdAt": "2022-05-14T04:06:52.000Z", "signatureCount": 5000}, {"__typename": "MilestonePetitionUpdate", "id": "30529892", "createdAt": "2022-05-09T10:31:32.000Z", "signatureCount": 4000}], "pageInfo": {"endCursor": "YXJyYXljb25uZWN0aW9uOjEx", "hasNextPage": true}}}}}, {"data": {"petition": {"id": "33174933", "slug": "remove-amber-heard-as-an-aclu-ambassador", "user": {"id": "6021991", "displayName": "Georgia Ota", "photo": {"id": "215978692", "userSmall": {"url": "//assets.change.org/photos/4/rn/dh/MMRnDHHbRdZoCWu-48x48-noPad.jpg?1516582206", "processing": false}}}, "organization": null, "updatesConnection": {"nodes": [{"__typename": "MilestonePetitionUpdate", "id": "30522665", "createdAt": "2022-05-06T22:52:49.000Z", "signatureCount": 3000}, {"__typename": "MilestonePetitionUpdate", "id": "30517954", "createdAt": "2022-05-05T20:15:45.000Z", "signatureCount": 2500}, {"__typename": "MilestonePetitionUpdate", "id": "30512504", "createdAt": "2022-05-04T15:10:31.000Z", "signatureCount": 2000}, {"__typename": "MilestonePetitionUpdate", "id": "30505488", "createdAt": "2022-05-02T20:18:10.000Z", "signatureCount": 1500}, {"__typename": "MilestonePetitionUpdate", "id": "30502181", "createdAt": "2022-05-01T20:25:21.000Z", "signatureCount": 1000}, {"__typename": "StarterPetitionUpdate", "id": "30498774", "createdAt": "2022-04-30T16:15:12.000Z", "title": "We\u2019re almost there", "description": "<p>Please considering sharing this petition. At 1000 signatures I will forward the results to ACLU Executive Director Anthony D Romero and express our request to have Amber Heard removed as Ambassador. Thank you so much for your help.\u00a0</p>", "photo": null, "video": null, "embeddedMedia": null}, {"__typename": "MilestonePetitionUpdate", "id": "30498503", "createdAt": "2022-04-30T14:24:09.000Z", "signatureCount": 750}, {"__typename": "MilestonePetitionUpdate", "id": "30496670", "createdAt": "2022-04-29T22:24:29.000Z", "signatureCount": 500}, {"__typename": "MilestonePetitionUpdate", "id": "30493298", "createdAt": "2022-04-29T02:20:43.000Z", "signatureCount": 250}, {"__typename": "MilestonePetitionUpdate", "id": "30493044", "createdAt": "2022-04-29T00:51:03.000Z", "signatureCount": 200}, {"__typename": "MilestonePetitionUpdate", "id": "30492845", "createdAt": "2022-04-28T23:42:55.000Z", "signatureCount": 100}, {"__typename": "MilestonePetitionUpdate", "id": "30492813", "createdAt": "2022-04-28T23:29:17.000Z", "signatureCount": 50}], "pageInfo": {"endCursor": "YXJyYXljb25uZWN0aW9uOjIz", "hasNextPage": true}}}}}, {"data": {"petition": {"id": "33174933", "slug": "remove-amber-heard-as-an-aclu-ambassador", "user": {"id": "6021991", "displayName": "Georgia Ota", "photo": {"id": "215978692", "userSmall": {"url": "//assets.change.org/photos/4/rn/dh/MMRnDHHbRdZoCWu-48x48-noPad.jpg?1516582206", "processing": false}}}, "organization": null, "updatesConnection": {"nodes": [{"__typename": "MilestonePetitionUpdate", "id": "30492788", "createdAt": "2022-04-28T23:22:10.000Z", "signatureCount": 25}, {"__typename": "MilestonePetitionUpdate", "id": "30492751", "createdAt": "2022-04-28T23:10:25.000Z", "signatureCount": 10}, {"__typename": "MilestonePetitionUpdate", "id": "30492743", "createdAt": "2022-04-28T23:06:49.000Z", "signatureCount": 5}], "pageInfo": {"endCursor": "YXJyYXljb25uZWN0aW9uOjI2", "hasNextPage": false}}}}}], "count": 3, "cursors": ["", "YXJyYXljb25uZWN0aW9uOjEx", "YXJyYXljb25uZWN0aW9uOjIz"]}